firebaseHelper/__init__.py
firebaseHelper/firebaseHelper.py
firebaseHelper-0.0.1.dist-info/LICENSE
firebaseHelper-0.0.1.dist-info/METADATA
firebaseHelper-0.0.1.dist-info/WHEEL
firebaseHelper-0.0.1.dist-info/top_level.txt
firebaseHelper-0.0.1.dist-info/RECORD
